wanderer/__init__.py
wanderer/admin.py
wanderer/apps.py
wanderer/auth_hooks.py
wanderer/cache.py
wanderer/forms.py
wanderer/http_client.py
wanderer/managers.py
wanderer/models.py
wanderer/signals.py
wanderer/tasks.py
wanderer/urls.py
wanderer/utils.py
wanderer/views.py
wanderer/wanderer.py
wanderer/locale/en/LC_MESSAGES/django.po
wanderer/management/commands/wanderer_cleanup_acls.py
wanderer/migrations/0001_initial.py
wanderer/migrations/0002_add_admin_manager_fields.py
wanderer/migrations/0003_add_performance_indexes.py
wanderer/migrations/__init__.py
wanderer/templates/wanderer/wmm_services_ctrl.html
wanderer/tests/__init__.py
wanderer/tests/test_api.py
wanderer/tests/test_cache.py
wanderer/tests/test_http_client.py
wanderer/tests/test_map.py
wanderer/tests/test_performance.py
wanderer/tests/test_tasks.py
wanderer/tests/test_utils.py
wanderer/tests/utils.py
aa_wanderer_map-0.1.7.dist-info/licenses/LICENSE
aa_wanderer_map-0.1.7.dist-info/WHEEL
aa_wanderer_map-0.1.7.dist-info/METADATA
aa_wanderer_map-0.1.7.dist-info/RECORD
