Metadata-Version: 2.4
Name: aa-wanderer-map
Version: 0.1.7
Summary: AA wanderer
Author-email: guarzo <guarzo@users.noreply.github.com>
Maintainer-email: guarzo <guarzo@users.noreply.github.com>
Requires-Python: >=3.10
Classifier: Environment :: Web Environment
Classifier: Framework :: Django
Classifier: Framework :: Django :: 4.2
Classifier: Intended Audience :: Developers
Classifier: License :: OSI Approved :: MIT License
Classifier: Operating System :: OS Independent
Classifier: Programming Language :: Python
Classifier: Programming Language :: Python :: 3.10
Classifier: Programming Language :: Python :: 3.11
Classifier: Programming Language :: Python :: 3.12
Classifier: Programming Language :: Python :: 3.13
Classifier: Topic :: Internet :: WWW/HTTP
Classifier: Topic :: Internet :: WWW/HTTP :: Dynamic Content
License-File: LICENSE
Requires-Dist: allianceauth>=4
Requires-Dist: allianceauth-app-utils>=1.25
Project-URL: Changelog, https://github.com/guarzo/aa-wanderer-map/blob/main/CHANGELOG.md
Project-URL: Homepage, https://github.com/guarzo/aa-wanderer-map
Project-URL: Source, https://github.com/guarzo/aa-wanderer-map
Project-URL: Tracker, https://github.com/guarzo/aa-wanderer-map/issues
